README.md
setup.py
wrestlr/__init__.py
wrestlr/ast.py
wrestlr/call_nodes.py
wrestlr/magic.py
wrestlr/transformers.py
wrestlr.egg-info/PKG-INFO
wrestlr.egg-info/SOURCES.txt
wrestlr.egg-info/dependency_links.txt
wrestlr.egg-info/requires.txt
wrestlr.egg-info/top_level.txt
wrestlr/parsers/R/RLexer.py
wrestlr/parsers/R/RListener.py
wrestlr/parsers/R/RParser.py
wrestlr/parsers/R/RVisitor.py
wrestlr/parsers/R/__init__.py
wrestlr/tests/test_transforms.py