Metadata-Version: 1.0
Name: wrestlr
Version: 0.0.1
Summary: Why debate R vs python, when you could convert R to python?
Home-page: https://github.com/machow/wrestlr
Author: Michael Chow
Author-email: mc_al_github@fastmail.com
License: UNKNOWN
Platform: UNKNOWN
